<?xml version = '1.0' encoding = 'UTF-8'?>
<FKIndexAssociation class="oracle.dbtools.crest.model.design.relational.FKIndexAssociation" directorySegmentName="seg_0" id="3186F3DD-F2E2-7033-0CCD-4FBEA8A4B3B1" containerWithKeyObject="0F6B3B9E-379F-0174-F922-43CEC8C52BE4" localFKIndex="F493C045-1B61-DA96-A537-E1D256FC9283" name="rentals_customers_FK">
<createdBy>Yavor</createdBy>
<createdTime>2022-10-30 13:54:41 UTC</createdTime>
<ownerDesignName>car_rental</ownerDesignName>
<referredTableLongName>customers</referredTableLongName>
<deleteRule>NO ACTION</deleteRule>
<referredTableID>8C8249E0-7F62-9954-3242-FCA4C0F99E67</referredTableID>
<keyObject>26271E27-17E2-AE3E-DEDA-F7DAA4983864</keyObject>
<referredKeyID>26271E27-17E2-AE3E-DEDA-F7DAA4983864</referredKeyID>
<mandatory>true</mandatory>
<refColNames>customer_id</refColNames>
<transferable>true</transferable>
<rely>false</rely>
<columnDependencyConstraintGenerateInDDL>true</columnDependencyConstraintGenerateInDDL>
</FKIndexAssociation>
