<?xml version = '1.0' encoding = 'UTF-8'?>
<Level class="oracle.dbtools.crest.model.design.multidimensional.Level" name="City" directorySegmentName="seg_0" id="2C50EA89-8075-746E-8777-68AA6EF6B449">
<createdBy>Yavor</createdBy>
<createdTime>2025-04-11 12:24:08 UTC</createdTime>
<generatorID>7F1866B5-FD7F-43D8-9129-543662288BB2</generatorID>
<ownerDesignName>Finance</ownerDesignName>
<nameInOracleAW>CITY</nameInOracleAW>
<levelEntity>B6FCC548-6C53-F308-408A-CC2FCD9CAD6F</levelEntity>
<oraDimension>Branch_Dim</oraDimension>
<rootIdentification>ParentIsBlankSelfOrMissing</rootIdentification>
<valueBasedHierarchy>false</valueBasedHierarchy>
<oraAWAttributes class="oracle.dbtools.crest.model.design.multidimensional.Level$OraAWAttributes">
</oraAWAttributes>
<levelKey>
<attribute>27812475-12BB-6C6C-B721-8F5729D30772</attribute>
</levelKey>
<descriptiveAttributes>
<descrAttribute class="oracle.dbtools.crest.model.design.multidimensional.SlowChangingAttribute" name="name" id="A8AED543-7127-D0C0-055B-CEC29121B5C2">
<createdBy>Yavor</createdBy>
<createdTime>2025-04-11 12:24:08 UTC</createdTime>
<ownerDesignName>Finance</ownerDesignName>
<attribute>336F0CB0-14A1-A88A-58D8-7E6F2931856B</attribute>
<classification>USER</classification>
<indexed>false</indexed>
<type>NONE</type>
</descrAttribute>
</descriptiveAttributes>
</Level>
